{
 "SoundBanksInfo": {
  "Platform": "Windows",
  "BasePlatform": "Windows",
  "SchemaVersion": "16",
  "SoundBankVersion": "154",
  "SoundBanks": [
   {
    "Id": "1658100665",
    "Type": "Event",
    "GUID": "{AB30D5A1-07FA-4425-B1DA-5FE115BC1EFA}",
    "Language": "SFX",
    "Hash": "{DDFA0094-28F5-49DA-E059-AC8D2ED8160C}",
    "ObjectPath": "Stop_AMB_WaitRoom",
    "ShortName": "Stop_AMB_WaitRoom",
    "Path": "Event/Stop_AMB_WaitRoom.bnk",
    "Events": [
     {
      "Id": "1658100665",
      "Name": "Stop_AMB_WaitRoom",
      "ObjectPath": "\\Events\\Default Work Unit\\AMB\\Stop_AMB_WaitRoom",
      "GUID": "{AB30D5A1-07FA-4425-B1DA-5FE115BC1EFA}",
      "MaxAttenuation": "0",
      "DurationType": "OneShot",
      "DurationMin": "0",
      "DurationMax": "0"
     }
    ]
   }
  ],
  "FileHash": "{21C59F69-3364-2E19-0D6A-5A83CF0E613D}"
 }
}